ff_storage/__init__.py
ff_storage/exceptions.py
ff_storage/health.py
ff_storage/db/__init__.py
ff_storage/db/adapters.py
ff_storage/db/sql.py
ff_storage/db/connections/__init__.py
ff_storage/db/connections/mysql.py
ff_storage/db/connections/postgres.py
ff_storage/db/connections/sqlserver.py
ff_storage/db/query_builder/__init__.py
ff_storage/db/query_builder/base.py
ff_storage/db/query_builder/mysql.py
ff_storage/db/query_builder/postgres.py
ff_storage/db/query_builder/sqlserver.py
ff_storage/db/schema_sync/__init__.py
ff_storage/db/schema_sync/async_introspector.py
ff_storage/db/schema_sync/async_manager.py
ff_storage/db/schema_sync/base.py
ff_storage/db/schema_sync/manager.py
ff_storage/db/schema_sync/models.py
ff_storage/db/schema_sync/mysql.py
ff_storage/db/schema_sync/normalizer.py
ff_storage/db/schema_sync/postgres.py
ff_storage/db/schema_sync/sqlserver.py
ff_storage/erd/__init__.py
ff_storage/erd/builder.py
ff_storage/erd/mermaid.py
ff_storage/erd/models.py
ff_storage/mock/__init__.py
ff_storage/mock/cascade.py
ff_storage/mock/extensions.py
ff_storage/mock/factory.py
ff_storage/mock/generators/__init__.py
ff_storage/mock/generators/pattern_generators.py
ff_storage/mock/generators/registry.py
ff_storage/mock/generators/type_generators.py
ff_storage/object/__init__.py
ff_storage/object/azure_blob.py
ff_storage/object/base.py
ff_storage/object/local.py
ff_storage/object/s3.py
ff_storage/pydantic_support/__init__.py
ff_storage/pydantic_support/base.py
ff_storage/pydantic_support/field_metadata.py
ff_storage/pydantic_support/introspector.py
ff_storage/pydantic_support/repository.py
ff_storage/pydantic_support/type_mapping.py
ff_storage/query/__init__.py
ff_storage/query/aggregations.py
ff_storage/query/builder.py
ff_storage/query/bulk.py
ff_storage/query/constants.py
ff_storage/query/executor.py
ff_storage/query/expressions.py
ff_storage/query/functions.py
ff_storage/query/ordering.py
ff_storage/query/sql_utils.py
ff_storage/query/subquery.py
ff_storage-4.9.0.dist-info/licenses/LICENSE
ff_storage-4.9.0.dist-info/METADATA
ff_storage-4.9.0.dist-info/WHEEL
ff_storage-4.9.0.dist-info/top_level.txt
ff_storage-4.9.0.dist-info/RECORD
