Metadata-Version: 2.4
Name: ff-storage
Version: 4.9.0
Summary: Fenixflow storage package with Pydantic ORM, temporal data management, and state-based schema sync
Author-email: Ben Moag <dev@fenixflow.com>
Maintainer-email: Fenixflow Team <dev@fenixflow.com>
Project-URL: Homepage, https://fenixflow.com
Project-URL: Repository, https://gitlab.com/fenixflow/fenix-packages
Project-URL: Documentation, https://gitlab.com/fenixflow/fenix-packages/-/tree/main/ff-storage
Project-URL: Bug Tracker, https://gitlab.com/fenixflow/fenix-packages/-/issues
Project-URL: Changelog, https://gitlab.com/fenixflow/fenix-packages/-/blob/main/ff-storage/CHANGELOG.md
Keywords: storage,database,postgresql,mysql,sqlserver,s3,object-storage,file-storage,migrations,fenixflow
Classifier: Development Status :: 4 - Beta
Classifier: Intended Audience :: Developers
Classifier: License :: OSI Approved :: MIT License
Classifier: Operating System :: OS Independent
Classifier: Programming Language :: Python
Classifier: Programming Language :: Python :: 3
Classifier: Programming Language :: Python :: 3.10
Classifier: Programming Language :: Python :: 3.11
Classifier: Programming Language :: Python :: 3.12
Classifier: Topic :: Software Development :: Libraries :: Python Modules
Classifier: Topic :: Database
Classifier: Topic :: System :: Filesystems
Classifier: Typing :: Typed
Requires-Python: >=3.10
License-File: LICENSE
Requires-Dist: pydantic>=2.0
Requires-Dist: psycopg2-binary>=2.9
Requires-Dist: asyncpg>=0.29
Requires-Dist: pymysql>=1.1
Requires-Dist: mysql-connector-python>=8.0
Requires-Dist: aiomysql>=0.2.0
Requires-Dist: pyodbc>=5.0
Requires-Dist: aioodbc>=0.5.0
Requires-Dist: boto3>=1.34
Requires-Dist: azure-storage-blob>=12.19
Requires-Dist: azure-identity>=1.17.0
Requires-Dist: aiofiles>=23.0.0
Requires-Dist: aioboto3>=12.0.0
Requires-Dist: faker>=22.0
Provides-Extra: dev
Requires-Dist: pytest>=7.4; extra == "dev"
Requires-Dist: pytest-asyncio>=0.21; extra == "dev"
Requires-Dist: black>=23.0; extra == "dev"
Requires-Dist: ruff>=0.1; extra == "dev"
Requires-Dist: moto[s3]>=5.0.0; extra == "dev"
Requires-Dist: aioboto3>=12.0.0; extra == "dev"
Dynamic: license-file
